[
  {
    "first_name": "EA",
    "last_name": "Sport",
    "id": "87181d84e2cf52"
  },
  {
    "first_name": "J.R.R",
    "last_name": "Tolkien",
    "id": "4ba3b5f7de5cc2"
  },
  {
    "first_name": "George.R.R",
    "last_name": "Martin",
    "id": "5ba3b5fcde5cc2"
  },
  {
    "first_name": "Madelaine",
    "last_name": "Miller",
    "id": "1c408406ea9a1c"
  },
  {
    "first_name": "Smark",
    "last_name": "Down",
    "id": "95bb68dd71cba6"
  },
  {
    "first_name": "EA",
    "last_name": "Sport",
    "id": "7e29d301fe7db9"
  },
  {
    "first_name": "Sendy",
    "last_name": "Michale",
    "id": "5aae010964813b"
  }
]